{"type": "Feature", "id": 12510833, "geometry": {"type": "Point", "coordinates": [-59.4939, 13.0719]}, "properties": {"woe:id": 12510833, "woe:parent_id": 56686, "woe:name": "Grantley Adams International Airport", "woe:placetype": 14, "woe:placetype_name": "Airport", "woe:lang": "ENG", "iso:country": "BB", "meta:provider": ["geoplanet:7.3.1", "geoplanet:7.3.2", "geoplanet:7.4.0", "geoplanet:7.4.1", "geoplanet:7.5.1", "geoplanet:7.5.2", "geoplanet:7.6.0", "geoplanet:7.8.1", "geoplanet:7.9.0", "geoplanet:7.10.0", "geoplanet:8.0.0", "woeplanet:8.0.0"], "meta:indexed": "2020-08-20T20:49:06.677803", "woe:alias_ENG_V": ["BGI Airport", "Grantley Adams", "Grantley Adams Airport", "Grantley Adams International", "BGI"], "meta:updated": "2020-10-14T11:14:59.146459", "woe:hierarchy": {"continent": 24865672, "country": 23424754, "town": 0, "planet": 1, "county": 0, "suburb": 0, "state": 2344730, "region": 0, "localadmin": 0}, "woe:timezone_id": 28350738, "woe:hash": "ddmdq5tv7dub", "woe:centroid": [-59.4939, 13.0719], "geom:latitude": 13.0719, "geom:longitude": -59.4939, "geom:hash": "ddmdq5tv7dub", "woe:latitude": 13.0719, "geom:centroid": [-59.4939, 13.0719], "woe:longitude": -59.4939, "woe:repo": "woeplanet-airport-bb", "geom:area": 0.0, "woe:scale": 19}}